Workbook

Sheet 00_Методика
A1: Методика оценки объема рынка электронного бизнеса по данным Similarweb
A3: Блок | B3: Цель | C3: Действие | D3: Что фиксировать | E3: Расчетный результат | F3: Ограничения | G3: Лист Excel | H3: Выходной вывод
A4: 1. Границы рынка | B4: Уточнить, какой рынок оценивается | C4: Зафиксировать продукт, географию, аудиторию и цифровые каналы | D4: Название рынка, территория, период, сегменты | E4: Паспорт расчетной модели | F4: Без границ рынка трафик конкурентов нельзя трактовать как объем рынка | G4: 01_Параметры | H4: Что именно считается рынком
A5: 2. Конкуренты | B5: Определить ядро цифрового рынка | C5: Собрать сайты прямых и частичных конкурентов | D5: Домен, сегмент, тип конкурента | E5: Список цифровых игроков | F5: Малые сайты могут отображаться неполно | G5: 02_Конкуренты_SW | H5: Кто формирует цифровое предложение
A6: 3. Трафик | B6: Оценить цифровой масштаб сегмента | C6: Внести посещения, географическую долю и релевантность | D6: Monthly visits, доля выбранной географии, релевантная доля | E6: Релевантный месячный и годовой трафик | F6: Трафик не равен покупкам | G6: 02_Конкуренты_SW | H6: Насколько велик цифровой поток аудитории
A7: 4. Каналы | B7: Понять структуру привлечения аудитории | C7: Разложить трафик по Direct, Organic, Referral, Social, Paid, Mail, Display | D7: Доли каналов по конкурентам | E7: Канальная структура рынка | F7: Доли каналов оценочные | G7: 03_Каналы | H7: Какие каналы важны для входа на рынок
A8: 5. География | B8: Проверить территориальную концентрацию спроса | C8: Сопоставить страны/регионы по доле трафика | D8: Страна, доля, интерпретация | E8: Приоритетные географии | F8: Доля трафика не равна платежеспособности | G8: 04_География | H8: Где целесообразно анализировать рынок
A9: 6. Поиск | B9: Определить коммерческий спрос внутри трафика | C9: Зафиксировать ключевые запросы и намерение аудитории | D9: Запрос, доля или объем, тип намерения | E9: Индекс коммерческого интереса | F9: Запросы видны неполно в бесплатном доступе | G9: 05_Запросы | H9: Какие потребности приводят аудиторию
A10: 7. Воронка | B10: Перевести трафик в возможные заказы | C10: Задать конверсии и средний чек | D10: CR в заявку, CR в продажу, средний чек | E10: Оценка объема рынка в деньгах | F10: Конверсии задаются сценарно | G10: 06_Воронка_сценарии | H10: Диапазон рынка по сценариям
A11: 8. Проверка | B11: Снизить риск завышения оценки | C11: Сопоставить расчет с другими источниками | D11: Google Trends, Вордстат, статистика, рекламные кабинеты | E11: Уточненный диапазон оценки | F11: Источники измеряют разные показатели | G11: 08_Источники | H11: Насколько расчет устойчив
A13: Ключевая расчетная логика
A14: 1 | B14: Наблюдаемый цифровой сегмент | C14: Сумма релевантного трафика выбранных конкурентов | D14: = сумма посещений × доля географии × доля релевантности
A15: 2 | B15: Оценка всего цифрового рынка | C15: Наблюдаемый сегмент / коэффициент покрытия конкурентов | D15: Если список конкурентов покрывает 70% рынка, общий рынок = наблюдаемый трафик / 70%
A16: 3 | B16: Оценка заявок | C16: Рыночный трафик × конверсия в заявку | D16: Конверсия задается по сценариям
A17: 4 | B17: Оценка продаж | C17: Заявки × конверсия в продажу | D17: Отражает платежеспособный спрос
A18: 5 | B18: Денежный объем | C18: Продажи × средний чек × повторные покупки | D18: Итоговый объем рынка за год

Sheet 01_Параметры
A1: Параметры оценки рынка
A3: Параметр | B3: Значение | C3: Единица / формат | D3: Комментарий
A4: Название рынка | B4: Цифровые маркетинговые услуги для малого бизнеса | C4: текст | D4: Замените на ваш рынок
A5: Географическая граница | B5: Республика Беларусь | C5: текст | D5: Страна, регион или город
A6: Период анализа | B6: последние 3 месяца | C6: текст | D6: Период, показанный в Similarweb
A7: Дата фиксации данных | B7: 46144 | C7: дата | D7: Дата ручного сбора или выгрузки
A8: Количество конкурентов в выборке | B8: =COUNT('02_Конкуренты_SW'!E4:E23) -> 5 | C8: формула | D8: Заполняется автоматически
A9: Наблюдаемый релевантный трафик, мес. | B9: =SUM('02_Конкуренты_SW'!G4:G23) -> 42561 | C9: посещения | D9: Сумма по конкурентам
A10: Наблюдаемый релевантный трафик, год | B10: =SUM('02_Конкуренты_SW'!H4:H23) -> 510732 | C10: посещения | D10: Годовая оценка
A11: Коэффициент покрытия конкурентов | B11: 0.7 | C11: % | D11: Оцените, какую долю рынка покрывает список конкурентов
A12: Оценка всего цифрового трафика рынка, мес. | B12: =IFERROR(B9/B11,0) -> 60801.429 | C12: посещения | D12: Наблюдаемый трафик / покрытие
A13: Оценка всего цифрового трафика рынка, год | B13: =IFERROR(B10/B11,0) -> 729617.14 | C13: посещения | D13: Наблюдаемый трафик / покрытие
A15: Правила заполнения
A16: 1 | B16: Сначала зафиксируйте границы рынка | C16: Без этого нельзя решить, какие сайты считать конкурентами
A17: 2 | B17: В Similarweb соберите данные по 5–20 сайтам | C17: Чем шире выборка, тем устойчивее оценка
A18: 3 | B18: Вносите только сопоставимый период | C18: Например, последние 3 месяца для всех сайтов
A19: 4 | B19: Разделяйте весь трафик и релевантный трафик | C19: Не все посещения сайта относятся к анализируемому рынку
A20: 5 | B20: Итог давайте диапазоном | C20: Осторожный, базовый и оптимистичный сценарии

Sheet 02_Конкуренты_SW
A1: Ввод данных Similarweb по конкурентам
A3: Домен | B3: Название / конкурент | C3: Сегмент | D3: Тип | E3: Monthly visits | F3: Доля выбранной географии | G3: Релевантный трафик, мес. | H3: Релевантный трафик, год | I3: Доля рынка по трафику | J3: Bounce rate | K3: Pages / visit | L3: Avg duration | M3: Direct | N3: Organic search | O3: Referral | P3: Social | Q3: Paid search | R3: Display | S3: Комментарий
A4: example-agency.by | B4: Маркетинговое агентство 1 | C4: маркетинговые услуги | D4: прямой | E4: 18500 | F4: 0.82 | G4: =IFERROR(E4*F4,0) -> 15170 | H4: =G4*12 -> 182040 | I4: =IFERROR(G4/SUM($G$4:$G$23),0) -> 0.3564296 | J4: 0.48 | K4: 3.1 | L4: 00:02:10 | M4: 0.28 | N4: 0.42 | O4: 0.08 | P4: 0.12 | Q4: 0.07 | R4: 0.03 | S4: Демонстрационные данные; заменить фактическими
A5: example-promo.by | B5: Агентство продвижения 2 | C5: реклама и продвижение | D5: прямой | E5: 12300 | F5: 0.76 | G5: =IFERROR(E5*F5,0) -> 9348 | H5: =G5*12 -> 112176 | I5: =IFERROR(G5/SUM($G$4:$G$23),0) -> 0.2196377 | J5: 0.52 | K5: 2.7 | L5: 00:01:55 | M5: 0.22 | N5: 0.5 | O5: 0.07 | P5: 0.1 | Q5: 0.09 | R5: 0.02 | S5: Демонстрационные данные
A6: example-smm.by | B6: SMM-студия | C6: социальные сети | D6: частичный | E6: 9800 | F6: 0.88 | G6: =IFERROR(E6*F6,0) -> 8624 | H6: =G6*12 -> 103488 | I6: =IFERROR(G6/SUM($G$4:$G$23),0) -> 0.20262682 | J6: 0.55 | K6: 2.4 | L6: 00:01:40 | M6: 0.24 | N6: 0.3 | O6: 0.05 | P6: 0.31 | Q6: 0.08 | R6: 0.02 | S6: Демонстрационные данные
A7: example-context.by | B7: Контекстная реклама | C7: рекламные кампании | D7: частичный | E7: 7200 | F7: 0.79 | G7: =IFERROR(E7*F7,0) -> 5688 | H7: =G7*12 -> 68256 | I7: =IFERROR(G7/SUM($G$4:$G$23),0) -> 0.13364348 | J7: 0.46 | K7: 3.4 | L7: 00:02:30 | M7: 0.3 | N7: 0.38 | O7: 0.06 | P7: 0.07 | Q7: 0.17 | R7: 0.02 | S7: Демонстрационные данные
A8: example-marketer.by | B8: Частный специалист | C8: консалтинг | D8: заменитель | E8: 4100 | F8: 0.91 | G8: =IFERROR(E8*F8,0) -> 3731 | H8: =G8*12 -> 44772 | I8: =IFERROR(G8/SUM($G$4:$G$23),0) -> 0.087662414 | J8: 0.6 | K8: 1.9 | L8: 00:01:10 | M8: 0.36 | N8: 0.44 | O8: 0.04 | P8: 0.09 | Q8: 0.05 | R8: 0.02 | S8: Демонстрационные данные
G9: =IFERROR(E9*F9,0) -> 0 | H9: =G9*12 -> 0 | I9: =IFERROR(G9/SUM($G$4:$G$23),0) -> 0
G10: =IFERROR(E10*F10,0) -> 0 | H10: =G10*12 -> 0 | I10: =IFERROR(G10/SUM($G$4:$G$23),0) -> 0
G11: =IFERROR(E11*F11,0) -> 0 | H11: =G11*12 -> 0 | I11: =IFERROR(G11/SUM($G$4:$G$23),0) -> 0
G12: =IFERROR(E12*F12,0) -> 0 | H12: =G12*12 -> 0 | I12: =IFERROR(G12/SUM($G$4:$G$23),0) -> 0
G13: =IFERROR(E13*F13,0) -> 0 | H13: =G13*12 -> 0 | I13: =IFERROR(G13/SUM($G$4:$G$23),0) -> 0
G14: =IFERROR(E14*F14,0) -> 0 | H14: =G14*12 -> 0 | I14: =IFERROR(G14/SUM($G$4:$G$23),0) -> 0
G15: =IFERROR(E15*F15,0) -> 0 | H15: =G15*12 -> 0 | I15: =IFERROR(G15/SUM($G$4:$G$23),0) -> 0
G16: =IFERROR(E16*F16,0) -> 0 | H16: =G16*12 -> 0 | I16: =IFERROR(G16/SUM($G$4:$G$23),0) -> 0
G17: =IFERROR(E17*F17,0) -> 0 | H17: =G17*12 -> 0 | I17: =IFERROR(G17/SUM($G$4:$G$23),0) -> 0
G18: =IFERROR(E18*F18,0) -> 0 | H18: =G18*12 -> 0 | I18: =IFERROR(G18/SUM($G$4:$G$23),0) -> 0
G19: =IFERROR(E19*F19,0) -> 0 | H19: =G19*12 -> 0 | I19: =IFERROR(G19/SUM($G$4:$G$23),0) -> 0
G20: =IFERROR(E20*F20,0) -> 0 | H20: =G20*12 -> 0 | I20: =IFERROR(G20/SUM($G$4:$G$23),0) -> 0
... G23: =IFERROR(E23*F23,0) -> 0 | H23: =G23*12 -> 0 | I23: =IFERROR(G23/SUM($G$4:$G$23),0) -> 0
A25: ИТОГО / среднее | E25: =SUM(E4:E23) -> 51900 | G25: =SUM(G4:G23) -> 42561 | H25: =SUM(H4:H23) -> 510732 | I25: =SUM(I4:I23) -> 1 | J25: =AVERAGE(J4:J23) -> 0.522 | K25: =AVERAGE(K4:K23) -> 2.7 | M25: =SUMPRODUCT($G$4:$G$23,M4:M23)/SUM($G$4:$G$23) -> 0.26840253 | N25: =SUMPRODUCT($G$4:$G$23,N4:N23)/SUM($G$4:$G$23) -> 0.40966331 | O25: =SUMPRODUCT($G$4:$G$23,O4:O23)/SUM($G$4:$G$23) -> 0.065545452 | P25: =SUMPRODUCT($G$4:$G$23,P4:P23)/SUM($G$4:$G$23) -> 0.1447943 | Q25: =SUMPRODUCT($G$4:$G$23,Q4:Q23)/SUM($G$4:$G$23) -> 0.088030121 | R25: =SUMPRODUCT($G$4:$G$23,R4:R23)/SUM($G$4:$G$23) -> 0.023564296

Sheet 03_Каналы
A1: Канальная структура рынка по данным Similarweb
A3: Канал | B3: Средневзвешенная доля | C3: Оценка рыночного трафика, мес. | D3: Оценка рыночного трафика, год | E3: Коммерческая интерпретация | F3: Что проверить дополнительно | G3: Ограничение | H3: Приоритет
A4: Direct | B4: ='02_Конкуренты_SW'!M25 -> 0.26840253 | C4: =B4*'01_Параметры'!$B$12 -> 16319.257 | D4: =C4*12 -> 195831.09 | E4: Сила бренда и повторные посещения | F4: Узнаваемость конкурентов, прямые заходы | G4: Не всегда означает новый спрос | H4: =IF(B4>=0.3,"высокий",IF(B4>=0.15,"средний","низкий")) -> средний
A5: Organic search | B5: ='02_Конкуренты_SW'!N25 -> 0.40966331 | C5: =B5*'01_Параметры'!$B$12 -> 24908.114 | D5: =C5*12 -> 298897.37 | E5: Поисковый спрос и эффективность содержания | F5: Семантическое ядро, видимость в поиске | G5: Запросы могут быть информационными | H5: =IF(B5>=0.3,"высокий",IF(B5>=0.15,"средний","низкий")) -> высокий
A6: Referral | B6: ='02_Конкуренты_SW'!O25 -> 0.065545452 | C6: =B6*'01_Параметры'!$B$12 -> 3985.2571 | D6: =C6*12 -> 47823.086 | E6: Партнерские и справочные источники | F6: Каталоги, публикации, партнеры | G6: Часть переходов может быть нерелевантна | H6: =IF(B6>=0.3,"высокий",IF(B6>=0.15,"средний","низкий")) -> низкий
A7: Social | B7: ='02_Конкуренты_SW'!P25 -> 0.1447943 | C7: =B7*'01_Параметры'!$B$12 -> 8803.7 | D7: =C7*12 -> 105644.4 | E7: Спрос через социальные сети | F7: Активность в соцсетях и сообществах | G7: Социальный трафик не всегда конверсионный | H7: =IF(B7>=0.3,"высокий",IF(B7>=0.15,"средний","низкий")) -> низкий
A8: Paid search | B8: ='02_Конкуренты_SW'!Q25 -> 0.088030121 | C8: =B8*'01_Параметры'!$B$12 -> 5352.3571 | D8: =C8*12 -> 64228.286 | E8: Платный спрос и рекламная конкуренция | F8: Стоимость клика, рекламные объявления | G8: Высокая доля может отражать закупку трафика | H8: =IF(B8>=0.3,"высокий",IF(B8>=0.15,"средний","низкий")) -> низкий
A9: Display | B9: ='02_Конкуренты_SW'!R25 -> 0.023564296 | C9: =B9*'01_Параметры'!$B$12 -> 1432.7429 | D9: =C9*12 -> 17192.914 | E9: Медийная реклама и охват | F9: Баннеры, ретаргетинг | G9: Слабее связан с намерением покупки | H9: =IF(B9>=0.3,"высокий",IF(B9>=0.15,"средний","низкий")) -> низкий

Sheet 04_География
A1: Географическая структура цифрового рынка
A3: Страна / регион | B3: Доля трафика по Similarweb | C3: Оценка месячного трафика рынка | D3: Оценка годового трафика рынка | E3: Платежеспособность / доступность | F3: Конкурентная плотность | G3: Приоритет рынка | H3: Комментарий
A4: Республика Беларусь | B4: 0.78 | C4: =B4*'01_Параметры'!$B$12 -> 47425.114 | D4: =C4*12 -> 569101.37 | E4: средняя | F4: средняя | G4: =IF(B4>=0.35,"высокий",IF(B4>=0.15,"средний","низкий")) -> высокий | H4: Основная география анализа
A5: Минск | B5: 0.42 | C5: =B5*'01_Параметры'!$B$12 -> 25536.6 | D5: =C5*12 -> 306439.2 | E5: выше средней | F5: высокая | G5: =IF(B5>=0.35,"высокий",IF(B5>=0.15,"средний","низкий")) -> высокий | H5: Возможный стартовый сегмент
A6: Областные центры РБ | B6: 0.25 | C6: =B6*'01_Параметры'!$B$12 -> 15200.357 | D6: =C6*12 -> 182404.29 | E6: средняя | F6: средняя | G6: =IF(B6>=0.35,"высокий",IF(B6>=0.15,"средний","низкий")) -> средний | H6: Расширение после проверки Минска
A7: Другие русскоязычные рынки | B7: 0.17 | C7: =B7*'01_Параметры'!$B$12 -> 10336.243 | D7: =C7*12 -> 124034.91 | E7: разная | F7: высокая | G7: =IF(B7>=0.35,"высокий",IF(B7>=0.15,"средний","низкий")) -> средний | H7: Только при дистанционной модели оказания услуги

Sheet 05_Запросы
A1: Поисковые запросы и коммерческий интерес
A3: Запрос / ключевая фраза | B3: Источник | C3: Доля поискового трафика | D3: Оценочный месячный трафик | E3: Тип намерения | F3: Коммерческий вес | G3: Индекс коммерческого интереса | H3: Сегмент | I3: Решение | J3: Комментарий
A4: маркетинговое агентство | B4: Similarweb / Search | C4: 0.18 | D4: =C4*'01_Параметры'!$B$12 -> 10944.257 | E4: коммерческий | F4: 1 | G4: =D4*F4 -> 10944.257 | H4: агентство | I4: включить | J4: Поиск поставщика услуги
A5: продвижение бизнеса | B5: Similarweb / Search | C5: 0.15 | D5: =C5*'01_Параметры'!$B$12 -> 9120.2143 | E5: проблемный | F5: 0.8 | G5: =D5*F5 -> 7296.1714 | H5: рост продаж | I5: включить | J5: Потребность в клиентах
A6: настройка рекламы | B6: Similarweb / Search | C6: 0.13 | D6: =C6*'01_Параметры'!$B$12 -> 7904.1857 | E6: коммерческий | F6: 1 | G6: =D6*F6 -> 7904.1857 | H6: реклама | I6: включить | J6: Близко к покупке
A7: smm продвижение | B7: Similarweb / Search | C7: 0.11 | D7: =C7*'01_Параметры'!$B$12 -> 6688.1571 | E7: инструментальный | F7: 0.7 | G7: =D7*F7 -> 4681.71 | H7: соцсети | I7: включить | J7: Отдельное направление
A8: как привлечь клиентов | B8: Similarweb / Search | C8: 0.09 | D8: =C8*'01_Параметры'!$B$12 -> 5472.1286 | E8: проблемный | F8: 0.6 | G8: =D8*F8 -> 3283.2771 | H8: лидогенерация | I8: включить | J8: Потребность требует коммерческой проверки
A9: курсы маркетинга | B9: Similarweb / Search | C9: 0.08 | D9: =C9*'01_Параметры'!$B$12 -> 4864.1143 | E9: обучающий | F9: 0.3 | G9: =D9*F9 -> 1459.2343 | H9: обучение | I9: исключить/отдельно | J9: Не основной спрос на услугу
A10: что такое маркетинг | B10: Similarweb / Search | C10: 0.06 | D10: =C10*'01_Параметры'!$B$12 -> 3648.0857 | E10: информационный | F10: 0.1 | G10: =D10*F10 -> 364.80857 | H10: общий интерес | I10: исключить | J10: Не подтверждает платежеспособный спрос

Sheet 06_Воронка_сценарии
A1: Расчет объема рынка через цифровую воронку и сценарии
A3: Сценарные допущения
A4: Сценарий | B4: Коэффициент покрытия конкурентов | C4: Оценка рынка: посещения/мес. | D4: Конверсия в заявку | E4: Конверсия заявки в продажу | F4: Средний чек | G4: Покупок/клиента в год | H4: Заказов/мес. | I4: Выручка/мес. | J4: Выручка/год
A5: Осторожный | B5: 0.8 | C5: =IFERROR('01_Параметры'!$B$9/B5,0) -> 53201.25 | D5: 0.008 | E5: 0.18 | F5: 350 | G5: 1 | H5: =C5*D5*E5 -> 76.6098 | I5: =H5*F5 -> 26813.43 | J5: =I5*12*G5 -> 321761.16
A6: Базовый | B6: 0.7 | C6: =IFERROR('01_Параметры'!$B$9/B6,0) -> 60801.429 | D6: 0.015 | E6: 0.25 | F6: 500 | G6: 1.5 | H6: =C6*D6*E6 -> 228.00536 | I6: =H6*F6 -> 114002.68 | J6: =I6*12*G6 -> 2052048.2
A7: Оптимистичный | B7: 0.55 | C7: =IFERROR('01_Параметры'!$B$9/B7,0) -> 77383.636 | D7: 0.025 | E7: 0.35 | F7: 800 | G7: 2 | H7: =C7*D7*E7 -> 677.10682 | I7: =H7*F7 -> 541685.45 | J7: =I7*12*G7 -> 13000451
A10: Достижимая доля нового бизнеса (SOM)
A11: Сценарий | B11: Рыночная выручка/год | C11: Достижимая доля нового бизнеса | D11: Потенциальная выручка нового бизнеса/год | E11: Комментарий | F11: Ограничение
A12: Осторожный | B12: =J5 -> 321761.16 | C12: 0.005 | D12: =B12*C12 -> 1608.8058 | E12: Первые клиенты, тестирование канала | F12: Не учитывать как гарантированный доход
A13: Базовый | B13: =J6 -> 2052048.2 | C13: 0.015 | D13: =B13*C13 -> 30780.723 | E13: Устойчивый канал привлечения | F13: Требуется конкурентный анализ
A14: Оптимистичный | B14: =J7 -> 13000451 | C14: 0.035 | D14: =B14*C14 -> 455015.78 | E14: Сильное позиционирование и повторные продажи | F14: Требуется подтверждение продажами
A17: Формула итогового вывода
A18: Оценочный цифровой объем рынка за год определяется как диапазон между осторожным и оптимистичным сценариями.
A19: Минимум | C19: База | E19: Максимум | G19: Единица | H19: руб./год
A20: =A12 -> Осторожный | B20: =D12 -> 1608.8058 | C20: =A13 -> Базовый | D20: =D13 -> 30780.723 | E20: =A14 -> Оптимистичный | F20: =D14 -> 455015.78
A21: Рыночная выручка минимум | B21: =J5 -> 321761.16 | C21: Рыночная выручка база | D21: =J6 -> 2052048.2 | E21: Рыночная выручка максимум | F21: =J7 -> 13000451
A22: Вывод | B22: ="При заданных допущениях годовой объем цифрового рынка оценивается в диапазоне от "&TEXT(J5,"# ##0")&" до "&TEXT(J7,"# ##0")&" руб., а достижимая выручка нового бизнеса — от "&TEXT(D12,"# ##0")&" до "&TEXT(D14,"# ##0")&" руб. в год." -> При заданных допущениях годовой объем цифрового рынка оценивается в диапазоне от 321 761 до 13000 451 руб., а достижимая выручка нового бизнеса — от 1 609 до 455 016 руб. в год.

Sheet 07_Дашборд
A1: Итоговая панель оценки объема рынка по Similarweb
A3: Ключевые показатели
A4: Рынок | B4: ='01_Параметры'!B4 -> Цифровые маркетинговые услуги для малого бизнеса | C4: География | D4: ='01_Параметры'!B5 -> Республика Беларусь | E4: Конкурентов | F4: ='01_Параметры'!B8 -> 5 | G4: Наблюдаемый трафик/мес. | H4: ='01_Параметры'!B9 -> 42561 | I4: Оценка трафика рынка/мес. | J4: ='01_Параметры'!B12 -> 60801.429
A5: Осторожный рынок/год | B5: ='06_Воронка_сценарии'!J5 -> 321761.16 | C5: Базовый рынок/год | D5: ='06_Воронка_сценарии'!J6 -> 2052048.2 | E5: Оптимистичный рынок/год | F5: ='06_Воронка_сценарии'!J7 -> 13000451 | G5: SOM базовый/год | H5: ='06_Воронка_сценарии'!D13 -> 30780.723 | I5: Главный канал | J5: =INDEX('03_Каналы'!A4:A9,MATCH(MAX('03_Каналы'!B4:B9),'03_Каналы'!B4:B9,0)) -> Organic search
A6: Главный конкурент | B6: =INDEX('02_Конкуренты_SW'!B4:B23,MATCH(MAX('02_Конкуренты_SW'!G4:G23),'02_Конкуренты_SW'!G4:G23,0)) -> Маркетинговое агентство 1 | C6: Доля главного конкурента | D6: =MAX('02_Конкуренты_SW'!I4:I23) -> 0.3564296 | E6: Главный поисковый запрос | F6: =INDEX('05_Запросы'!A4:A10,MATCH(MAX('05_Запросы'!G4:G10),'05_Запросы'!G4:G10,0)) -> маркетинговое агентство | G6: Коммерческий индекс | H6: =MAX('05_Запросы'!G4:G10) -> 10944.257
A7: Итоговый вывод | B7: ='06_Воронка_сценарии'!B22 -> При заданных допущениях годовой объем цифрового рынка оценивается в диапазоне от 321 761 до 13000 451 руб., а достижимая выручка нового бизнеса — от 1 609 до 455 016 руб. в год.
A10: Сценарий | B10: Рынок, год | C10: SOM нового бизнеса, год
A11: Осторожный | B11: ='06_Воронка_сценарии'!J5 -> 321761.16 | C11: ='06_Воронка_сценарии'!D12 -> 1608.8058
A12: Базовый | B12: ='06_Воронка_сценарии'!J6 -> 2052048.2 | C12: ='06_Воронка_сценарии'!D13 -> 30780.723
A13: Оптимистичный | B13: ='06_Воронка_сценарии'!J7 -> 13000451 | C13: ='06_Воронка_сценарии'!D14 -> 455015.78
A16: Канал | B16: Доля | C16: Трафик/мес.
A17: Direct | B17: ='03_Каналы'!B4 -> 0.26840253 | C17: ='03_Каналы'!C4 -> 16319.257
A18: Organic search | B18: ='03_Каналы'!B5 -> 0.40966331 | C18: ='03_Каналы'!C5 -> 24908.114
A19: Referral | B19: ='03_Каналы'!B6 -> 0.065545452 | C19: ='03_Каналы'!C6 -> 3985.2571
A20: Social | B20: ='03_Каналы'!B7 -> 0.1447943 | C20: ='03_Каналы'!C7 -> 8803.7
A21: Paid search | B21: ='03_Каналы'!B8 -> 0.088030121 | C21: ='03_Каналы'!C8 -> 5352.3571
A22: Display | B22: ='03_Каналы'!B9 -> 0.023564296 | C22: ='03_Каналы'!C9 -> 1432.7429

Sheet 08_Источники
A1: Источники данных и журнал фиксации
A3: Источник | B3: Что брать | C3: Как фиксировать | D3: Ссылка | E3: Дата обращения | F3: Ограничение
A4: Similarweb Website Analysis | B4: Посещаемость, каналы, география, похожие сайты, поисковые запросы | C4: Ручной ввод или экспорт при наличии доступа | D4: https://www.similarweb.com/website/ | E4: 46144 | F4: Данные оценочные, полнота зависит от доступа
A5: Similarweb Data Methodology | B5: Описание природы и ограничений данных | C5: Использовать для методологических оговорок | D5: https://support.similarweb.com/hc/en-us/articles/360001631538-Similarweb-Data-Methodology | E5: 46144 | F5: Методология может обновляться
A6: Similarweb Data Exporter | B6: Выгрузка настраиваемых наборов данных | C6: Использовать при наличии платного доступа или единиц извлечения | D6: https://support.similarweb.com/hc/en-us/articles/13252032019101-Data-Exporter | E6: 46144 | F6: Может быть недоступно в бесплатной версии
A7: Google Trends | B7: Динамика относительного поискового интереса | C7: CSV-выгрузка и фиксация параметров | D7: https://trends.google.com/ | E7: 46144 | F7: Индекс 0–100, не абсолютный объем спроса
A8: Яндекс Вордстат | B8: Частотность и динамика поисковых запросов | C8: CSV/XLSX или ручная фиксация | D8: https://wordstat.yandex.ru/ | E8: 46144 | F8: Отражает аудиторию Яндекса
A9: Белстат / официальная статистика | B9: Количество организаций, отрасли, население, доходы | C9: Использовать для проверки сегмента клиентов | D9: https://www.belstat.gov.by/ | E9: 46144 | F9: Официальные категории могут не совпадать с цифровым рынком
A12: Журнал ручного сбора данных
A13: Дата | B13: Сайт / домен | C13: Раздел Similarweb | D13: Показатель | E13: Значение | F13: Комментарий / снимок экрана
A14: 46144 | B14: example-agency.by | C14: Traffic & Engagement | D14: Monthly visits | E14: 18500 | F14: Демонстрационная строка
